{
  "namespace": "OneStream.Shared.Wcf.DimensionLibraryServiceDto",
  "generated_at": "2025-12-08T19:28:52.393172",
  "statistics": {
    "classes": 29,
    "interfaces": 0,
    "structs": 0,
    "delegates": 0,
    "enums": 0,
    "total_methods": 0,
    "total_properties": 133
  },
  "classes": [
    {
      "name": "GetMemberAndRelationshipInfoCompressedRequestDto",
      "namespace": "OneStream.Shared.Wcf.DimensionLibraryServiceDto",
      "type": "class",
      "modifiers": [
        "public",
        "sealed"
      ],
      "base_class": null,
      "interfaces": [
        "IClientDto",
        "IAuthenticatedClientDto"
      ],
      "generic_params": [],
      "constructors": [],
      "properties": [
        {
          "name": "XfBytes",
          "type": "string",
          "access": "public",
          "has_getter": true,
          "has_setter": true,
          "is_static": false
        },
        {
          "name": "DimPk",
          "type": "DimPk",
          "access": "public",
          "has_getter": true,
          "has_setter": true,
          "is_static": false
        },
        {
          "name": "MemberId",
          "type": "int",
          "access": "public",
          "has_getter": true,
          "has_setter": true,
          "is_static": false
        },
        {
          "name": "ParentMemberId",
          "type": "int",
          "access": "public",
          "has_getter": true,
          "has_setter": true,
          "is_static": false
        },
        {
          "name": "DimDisplayOptions",
          "type": "DimDisplayOptions",
          "access": "public",
          "has_getter": true,
          "has_setter": true,
          "is_static": false
        }
      ],
      "methods": [],
      "events": [],
      "nested_types": [],
      "attributes": [],
      "source_file": "output/types/OneStream/Shared/Wcf/DimensionLibraryServiceDto/GetMemberAndRelationshipInfoCompressedRequestDto.cs"
    },
    {
      "name": "GetOrphanedMembersRequestDto",
      "namespace": "OneStream.Shared.Wcf.DimensionLibraryServiceDto",
      "type": "class",
      "modifiers": [
        "public",
        "sealed"
      ],
      "base_class": null,
      "interfaces": [
        "IClientDto",
        "IAuthenticatedClientDto"
      ],
      "generic_params": [],
      "constructors": [],
      "properties": [
        {
          "name": "XfBytes",
          "type": "string",
          "access": "public",
          "has_getter": true,
          "has_setter": true,
          "is_static": false
        },
        {
          "name": "DimPk",
          "type": "DimPk",
          "access": "public",
          "has_getter": true,
          "has_setter": true,
          "is_static": false
        },
        {
          "name": "MemberDisplayOptions",
          "type": "MemberDisplayOptions",
          "access": "public",
          "has_getter": true,
          "has_setter": true,
          "is_static": false
        }
      ],
      "methods": [],
      "events": [],
      "nested_types": [],
      "attributes": [],
      "source_file": "output/types/OneStream/Shared/Wcf/DimensionLibraryServiceDto/GetOrphanedMembersRequestDto.cs"
    },
    {
      "name": "GetRelationshipsUsingFilterCompressedRequestDto",
      "namespace": "OneStream.Shared.Wcf.DimensionLibraryServiceDto",
      "type": "class",
      "modifiers": [
        "public",
        "sealed"
      ],
      "base_class": null,
      "interfaces": [
        "IClientDto",
        "IAuthenticatedClientDto"
      ],
      "generic_params": [],
      "constructors": [],
      "properties": [
        {
          "name": "XfBytes",
          "type": "string",
          "access": "public",
          "has_getter": true,
          "has_setter": true,
          "is_static": false
        },
        {
          "name": "DimPk",
          "type": "DimPk",
          "access": "public",
          "has_getter": true,
          "has_setter": true,
          "is_static": false
        },
        {
          "name": "MemberFilter",
          "type": "string",
          "access": "public",
          "has_getter": true,
          "has_setter": true,
          "is_static": false
        },
        {
          "name": "DimDisplayOptions",
          "type": "DimDisplayOptions",
          "access": "public",
          "has_getter": true,
          "has_setter": true,
          "is_static": false
        },
        {
          "name": "MemberDisplayOptions",
          "type": "MemberDisplayOptions",
          "access": "public",
          "has_getter": true,
          "has_setter": true,
          "is_static": false
        },
        {
          "name": "MemberDisplayOptionsForParent",
          "type": "MemberDisplayOptions",
          "access": "public",
          "has_getter": true,
          "has_setter": true,
          "is_static": false
        }
      ],
      "methods": [],
      "events": [],
      "nested_types": [],
      "attributes": [],
      "source_file": "output/types/OneStream/Shared/Wcf/DimensionLibraryServiceDto/GetRelationshipsUsingFilterCompressedRequestDto.cs"
    },
    {
      "name": "GetAllMembersRequestDto",
      "namespace": "OneStream.Shared.Wcf.DimensionLibraryServiceDto",
      "type": "class",
      "modifiers": [
        "public",
        "sealed"
      ],
      "base_class": null,
      "interfaces": [
        "IClientDto",
        "IAuthenticatedClientDto"
      ],
      "generic_params": [],
      "constructors": [],
      "properties": [
        {
          "name": "XfBytes",
          "type": "string",
          "access": "public",
          "has_getter": true,
          "has_setter": true,
          "is_static": false
        },
        {
          "name": "DimPk",
          "type": "DimPk",
          "access": "public",
          "has_getter": true,
          "has_setter": true,
          "is_static": false
        },
        {
          "name": "IncludeInheritedDims",
          "type": "bool",
          "access": "public",
          "has_getter": true,
          "has_setter": true,
          "is_static": false
        },
        {
          "name": "DimDisplayOptions",
          "type": "DimDisplayOptions",
          "access": "public",
          "has_getter": true,
          "has_setter": true,
          "is_static": false
        },
        {
          "name": "MemberDisplayOptions",
          "type": "MemberDisplayOptions",
          "access": "public",
          "has_getter": true,
          "has_setter": true,
          "is_static": false
        }
      ],
      "methods": [],
      "events": [],
      "nested_types": [],
      "attributes": [],
      "source_file": "output/types/OneStream/Shared/Wcf/DimensionLibraryServiceDto/GetAllMembersRequestDto.cs"
    },
    {
      "name": "SaveDimRequestDto",
      "namespace": "OneStream.Shared.Wcf.DimensionLibraryServiceDto",
      "type": "class",
      "modifiers": [
        "public",
        "sealed"
      ],
      "base_class": null,
      "interfaces": [
        "IClientDto",
        "IAuthenticatedClientDto"
      ],
      "generic_params": [],
      "constructors": [],
      "properties": [
        {
          "name": "XfBytes",
          "type": "string",
          "access": "public",
          "has_getter": true,
          "has_setter": true,
          "is_static": false
        },
        {
          "name": "Dim",
          "type": "Dim",
          "access": "public",
          "has_getter": true,
          "has_setter": true,
          "is_static": false
        }
      ],
      "methods": [],
      "events": [],
      "nested_types": [],
      "attributes": [],
      "source_file": "output/types/OneStream/Shared/Wcf/DimensionLibraryServiceDto/SaveDimRequestDto.cs"
    },
    {
      "name": "CreateDimRequestDto",
      "namespace": "OneStream.Shared.Wcf.DimensionLibraryServiceDto",
      "type": "class",
      "modifiers": [
        "public",
        "sealed"
      ],
      "base_class": null,
      "interfaces": [
        "IClientDto",
        "IAuthenticatedClientDto"
      ],
      "generic_params": [],
      "constructors": [],
      "properties": [
        {
          "name": "XfBytes",
          "type": "string",
          "access": "public",
          "has_getter": true,
          "has_setter": true,
          "is_static": false
        },
        {
          "name": "Dim",
          "type": "Dim",
          "access": "public",
          "has_getter": true,
          "has_setter": true,
          "is_static": false
        }
      ],
      "methods": [],
      "events": [],
      "nested_types": [],
      "attributes": [],
      "source_file": "output/types/OneStream/Shared/Wcf/DimensionLibraryServiceDto/CreateDimRequestDto.cs"
    },
    {
      "name": "DeleteDimRequestDto",
      "namespace": "OneStream.Shared.Wcf.DimensionLibraryServiceDto",
      "type": "class",
      "modifiers": [
        "public",
        "sealed"
      ],
      "base_class": null,
      "interfaces": [
        "IClientDto",
        "IAuthenticatedClientDto"
      ],
      "generic_params": [],
      "constructors": [],
      "properties": [
        {
          "name": "XfBytes",
          "type": "string",
          "access": "public",
          "has_getter": true,
          "has_setter": true,
          "is_static": false
        },
        {
          "name": "DimPk",
          "type": "DimPk",
          "access": "public",
          "has_getter": true,
          "has_setter": true,
          "is_static": false
        }
      ],
      "methods": [],
      "events": [],
      "nested_types": [],
      "attributes": [],
      "source_file": "output/types/OneStream/Shared/Wcf/DimensionLibraryServiceDto/DeleteDimRequestDto.cs"
    },
    {
      "name": "MoveDimRequestDto",
      "namespace": "OneStream.Shared.Wcf.DimensionLibraryServiceDto",
      "type": "class",
      "modifiers": [
        "public",
        "sealed"
      ],
      "base_class": null,
      "interfaces": [
        "IClientDto",
        "IAuthenticatedClientDto"
      ],
      "generic_params": [],
      "constructors": [],
      "properties": [
        {
          "name": "XfBytes",
          "type": "string",
          "access": "public",
          "has_getter": true,
          "has_setter": true,
          "is_static": false
        },
        {
          "name": "DimPk",
          "type": "DimPk",
          "access": "public",
          "has_getter": true,
          "has_setter": true,
          "is_static": false
        },
        {
          "name": "NewInheritedDimId",
          "type": "int",
          "access": "public",
          "has_getter": true,
          "has_setter": true,
          "is_static": false
        }
      ],
      "methods": [],
      "events": [],
      "nested_types": [],
      "attributes": [],
      "source_file": "output/types/OneStream/Shared/Wcf/DimensionLibraryServiceDto/MoveDimRequestDto.cs"
    },
    {
      "name": "SaveMultipleMemberPropertiesRequestDto",
      "namespace": "OneStream.Shared.Wcf.DimensionLibraryServiceDto",
      "type": "class",
      "modifiers": [
        "public",
        "sealed"
      ],
      "base_class": null,
      "interfaces": [
        "IClientDto",
        "IAuthenticatedClientDto"
      ],
      "generic_params": [],
      "constructors": [],
      "properties": [
        {
          "name": "XfBytes",
          "type": "string",
          "access": "public",
          "has_getter": true,
          "has_setter": true,
          "is_static": false
        },
        {
          "name": "CubeTypeId",
          "type": "int",
          "access": "public",
          "has_getter": true,
          "has_setter": true,
          "is_static": false
        },
        {
          "name": "ScenarioTypeId",
          "type": "int",
          "access": "public",
          "has_getter": true,
          "has_setter": true,
          "is_static": false
        },
        {
          "name": "TimeId",
          "type": "int",
          "access": "public",
          "has_getter": true,
          "has_setter": true,
          "is_static": false
        },
        {
          "name": "DimPk",
          "type": "DimPk",
          "access": "public",
          "has_getter": true,
          "has_setter": true,
          "is_static": false
        },
        {
          "name": "SavingParentChildRelationshipProps",
          "type": "bool",
          "access": "public",
          "has_getter": true,
          "has_setter": true,
          "is_static": false
        },
        {
          "name": "MemberEditItems",
          "type": "MemberEditItemsCollection",
          "access": "public",
          "has_getter": true,
          "has_setter": true,
          "is_static": false
        }
      ],
      "methods": [],
      "events": [],
      "nested_types": [],
      "attributes": [],
      "source_file": "output/types/OneStream/Shared/Wcf/DimensionLibraryServiceDto/SaveMultipleMemberPropertiesRequestDto.cs"
    },
    {
      "name": "GetDescendantMembersCompressedRequestDto",
      "namespace": "OneStream.Shared.Wcf.DimensionLibraryServiceDto",
      "type": "class",
      "modifiers": [
        "public",
        "sealed"
      ],
      "base_class": null,
      "interfaces": [
        "IClientDto",
        "IAuthenticatedClientDto"
      ],
      "generic_params": [],
      "constructors": [],
      "properties": [
        {
          "name": "XfBytes",
          "type": "string",
          "access": "public",
          "has_getter": true,
          "has_setter": true,
          "is_static": false
        },
        {
          "name": "CubeIdOrUnknown",
          "type": "int",
          "access": "public",
          "has_getter": true,
          "has_setter": true,
          "is_static": false
        },
        {
          "name": "DimTypeId",
          "type": "int",
          "access": "public",
          "has_getter": true,
          "has_setter": true,
          "is_static": false
        },
        {
          "name": "DimId",
          "type": "int",
          "access": "public",
          "has_getter": true,
          "has_setter": true,
          "is_static": false
        },
        {
          "name": "MemberId",
          "type": "int",
          "access": "public",
          "has_getter": true,
          "has_setter": true,
          "is_static": false
        }
      ],
      "methods": [],
      "events": [],
      "nested_types": [],
      "attributes": [],
      "source_file": "output/types/OneStream/Shared/Wcf/DimensionLibraryServiceDto/GetDescendantMembersCompressedRequestDto.cs"
    },
    {
      "name": "GetDescendantMembersRequestDto",
      "namespace": "OneStream.Shared.Wcf.DimensionLibraryServiceDto",
      "type": "class",
      "modifiers": [
        "public",
        "sealed"
      ],
      "base_class": null,
      "interfaces": [
        "IClientDto",
        "IAuthenticatedClientDto"
      ],
      "generic_params": [],
      "constructors": [],
      "properties": [
        {
          "name": "XfBytes",
          "type": "string",
          "access": "public",
          "has_getter": true,
          "has_setter": true,
          "is_static": false
        },
        {
          "name": "CubeIdOrUnknown",
          "type": "int",
          "access": "public",
          "has_getter": true,
          "has_setter": true,
          "is_static": false
        },
        {
          "name": "DimTypeId",
          "type": "int",
          "access": "public",
          "has_getter": true,
          "has_setter": true,
          "is_static": false
        },
        {
          "name": "DimId",
          "type": "int",
          "access": "public",
          "has_getter": true,
          "has_setter": true,
          "is_static": false
        },
        {
          "name": "MemberId",
          "type": "int",
          "access": "public",
          "has_getter": true,
          "has_setter": true,
          "is_static": false
        }
      ],
      "methods": [],
      "events": [],
      "nested_types": [],
      "attributes": [],
      "source_file": "output/types/OneStream/Shared/Wcf/DimensionLibraryServiceDto/GetDescendantMembersRequestDto.cs"
    },
    {
      "name": "GetMemberAndRelationshipInfoRequestDto",
      "namespace": "OneStream.Shared.Wcf.DimensionLibraryServiceDto",
      "type": "class",
      "modifiers": [
        "public",
        "sealed"
      ],
      "base_class": null,
      "interfaces": [
        "IClientDto",
        "IAuthenticatedClientDto"
      ],
      "generic_params": [],
      "constructors": [],
      "properties": [
        {
          "name": "XfBytes",
          "type": "string",
          "access": "public",
          "has_getter": true,
          "has_setter": true,
          "is_static": false
        },
        {
          "name": "DimPk",
          "type": "DimPk",
          "access": "public",
          "has_getter": true,
          "has_setter": true,
          "is_static": false
        },
        {
          "name": "MemberId",
          "type": "int",
          "access": "public",
          "has_getter": true,
          "has_setter": true,
          "is_static": false
        },
        {
          "name": "ParentMemberId",
          "type": "int",
          "access": "public",
          "has_getter": true,
          "has_setter": true,
          "is_static": false
        },
        {
          "name": "DimDisplayOptions",
          "type": "DimDisplayOptions",
          "access": "public",
          "has_getter": true,
          "has_setter": true,
          "is_static": false
        }
      ],
      "methods": [],
      "events": [],
      "nested_types": [],
      "attributes": [],
      "source_file": "output/types/OneStream/Shared/Wcf/DimensionLibraryServiceDto/GetMemberAndRelationshipInfoRequestDto.cs"
    },
    {
      "name": "GetDimLibraryInitInfoCompressedRequestDto",
      "namespace": "OneStream.Shared.Wcf.DimensionLibraryServiceDto",
      "type": "class",
      "modifiers": [
        "public",
        "sealed"
      ],
      "base_class": null,
      "interfaces": [
        "IClientDto",
        "IAuthenticatedClientDto"
      ],
      "generic_params": [],
      "constructors": [],
      "properties": [
        {
          "name": "XfBytes",
          "type": "string",
          "access": "public",
          "has_getter": true,
          "has_setter": true,
          "is_static": false
        },
        {
          "name": "SelectedItem",
          "type": "MemberHierarchySelectedItem",
          "access": "public",
          "has_getter": true,
          "has_setter": true,
          "is_static": false
        }
      ],
      "methods": [],
      "events": [],
      "nested_types": [],
      "attributes": [],
      "source_file": "output/types/OneStream/Shared/Wcf/DimensionLibraryServiceDto/GetDimLibraryInitInfoCompressedRequestDto.cs"
    },
    {
      "name": "RemoveRelationshipsRequestDto",
      "namespace": "OneStream.Shared.Wcf.DimensionLibraryServiceDto",
      "type": "class",
      "modifiers": [
        "public",
        "sealed"
      ],
      "base_class": null,
      "interfaces": [
        "IClientDto",
        "IAuthenticatedClientDto"
      ],
      "generic_params": [],
      "constructors": [],
      "properties": [
        {
          "name": "XfBytes",
          "type": "string",
          "access": "public",
          "has_getter": true,
          "has_setter": true,
          "is_static": false
        },
        {
          "name": "DimPk",
          "type": "DimPk",
          "access": "public",
          "has_getter": true,
          "has_setter": true,
          "is_static": false
        },
        {
          "name": "RelationshipPks",
          "type": "List<RelationshipPk>",
          "access": "public",
          "has_getter": true,
          "has_setter": true,
          "is_static": false
        },
        {
          "name": "OkToRemoveChildFromLastRemainingParent",
          "type": "bool",
          "access": "public",
          "has_getter": true,
          "has_setter": true,
          "is_static": false
        }
      ],
      "methods": [],
      "events": [],
      "nested_types": [],
      "attributes": [],
      "source_file": "output/types/OneStream/Shared/Wcf/DimensionLibraryServiceDto/RemoveRelationshipsRequestDto.cs"
    },
    {
      "name": "GetDimLibraryInitInfoRequestDto",
      "namespace": "OneStream.Shared.Wcf.DimensionLibraryServiceDto",
      "type": "class",
      "modifiers": [
        "public",
        "sealed"
      ],
      "base_class": null,
      "interfaces": [
        "IClientDto",
        "IAuthenticatedClientDto"
      ],
      "generic_params": [],
      "constructors": [],
      "properties": [
        {
          "name": "XfBytes",
          "type": "string",
          "access": "public",
          "has_getter": true,
          "has_setter": true,
          "is_static": false
        },
        {
          "name": "SelectedItem",
          "type": "MemberHierarchySelectedItem",
          "access": "public",
          "has_getter": true,
          "has_setter": true,
          "is_static": false
        }
      ],
      "methods": [],
      "events": [],
      "nested_types": [],
      "attributes": [],
      "source_file": "output/types/OneStream/Shared/Wcf/DimensionLibraryServiceDto/GetDimLibraryInitInfoRequestDto.cs"
    },
    {
      "name": "GetMemberHierarchyInitInfoRequestDto",
      "namespace": "OneStream.Shared.Wcf.DimensionLibraryServiceDto",
      "type": "class",
      "modifiers": [
        "public",
        "sealed"
      ],
      "base_class": null,
      "interfaces": [
        "IClientDto",
        "IAuthenticatedClientDto"
      ],
      "generic_params": [],
      "constructors": [],
      "properties": [
        {
          "name": "XfBytes",
          "type": "string",
          "access": "public",
          "has_getter": true,
          "has_setter": true,
          "is_static": false
        },
        {
          "name": "SelectedItem",
          "type": "MemberHierarchySelectedItem",
          "access": "public",
          "has_getter": true,
          "has_setter": true,
          "is_static": false
        },
        {
          "name": "ExpandAll",
          "type": "bool",
          "access": "public",
          "has_getter": true,
          "has_setter": true,
          "is_static": false
        },
        {
          "name": "ExpandChildrenOfSelectedMember",
          "type": "bool",
          "access": "public",
          "has_getter": true,
          "has_setter": true,
          "is_static": false
        }
      ],
      "methods": [],
      "events": [],
      "nested_types": [],
      "attributes": [],
      "source_file": "output/types/OneStream/Shared/Wcf/DimensionLibraryServiceDto/GetMemberHierarchyInitInfoRequestDto.cs"
    },
    {
      "name": "CopyOrMoveRelationshipsRequestDto",
      "namespace": "OneStream.Shared.Wcf.DimensionLibraryServiceDto",
      "type": "class",
      "modifiers": [
        "public",
        "sealed"
      ],
      "base_class": null,
      "interfaces": [
        "IClientDto",
        "IAuthenticatedClientDto"
      ],
      "generic_params": [],
      "constructors": [],
      "properties": [
        {
          "name": "XfBytes",
          "type": "string",
          "access": "public",
          "has_getter": true,
          "has_setter": true,
          "is_static": false
        },
        {
          "name": "DimPk",
          "type": "DimPk",
          "access": "public",
          "has_getter": true,
          "has_setter": true,
          "is_static": false
        },
        {
          "name": "RelationshipPks",
          "type": "List<RelationshipPk>",
          "access": "public",
          "has_getter": true,
          "has_setter": true,
          "is_static": false
        },
        {
          "name": "NewParentId",
          "type": "int",
          "access": "public",
          "has_getter": true,
          "has_setter": true,
          "is_static": false
        },
        {
          "name": "IsCopyNotMove",
          "type": "bool",
          "access": "public",
          "has_getter": true,
          "has_setter": true,
          "is_static": false
        },
        {
          "name": "RelationshipPositionOptions",
          "type": "RelationshipPositionOptions",
          "access": "public",
          "has_getter": true,
          "has_setter": true,
          "is_static": false
        }
      ],
      "methods": [],
      "events": [],
      "nested_types": [],
      "attributes": [],
      "source_file": "output/types/OneStream/Shared/Wcf/DimensionLibraryServiceDto/CopyOrMoveRelationshipsRequestDto.cs"
    },
    {
      "name": "GetMembersUsingFilterCompressedRequestDto",
      "namespace": "OneStream.Shared.Wcf.DimensionLibraryServiceDto",
      "type": "class",
      "modifiers": [
        "public",
        "sealed"
      ],
      "base_class": null,
      "interfaces": [
        "IClientDto",
        "IAuthenticatedClientDto"
      ],
      "generic_params": [],
      "constructors": [],
      "properties": [
        {
          "name": "XfBytes",
          "type": "string",
          "access": "public",
          "has_getter": true,
          "has_setter": true,
          "is_static": false
        },
        {
          "name": "DimPk",
          "type": "DimPk",
          "access": "public",
          "has_getter": true,
          "has_setter": true,
          "is_static": false
        },
        {
          "name": "MemberFilter",
          "type": "string",
          "access": "public",
          "has_getter": true,
          "has_setter": true,
          "is_static": false
        },
        {
          "name": "DimDisplayOptions",
          "type": "DimDisplayOptions",
          "access": "public",
          "has_getter": true,
          "has_setter": true,
          "is_static": false
        },
        {
          "name": "MemberDisplayOptions",
          "type": "MemberDisplayOptions",
          "access": "public",
          "has_getter": true,
          "has_setter": true,
          "is_static": false
        },
        {
          "name": "RemoveDuplicates",
          "type": "bool",
          "access": "public",
          "has_getter": true,
          "has_setter": true,
          "is_static": false
        }
      ],
      "methods": [],
      "events": [],
      "nested_types": [],
      "attributes": [],
      "source_file": "output/types/OneStream/Shared/Wcf/DimensionLibraryServiceDto/GetMembersUsingFilterCompressedRequestDto.cs"
    },
    {
      "name": "GetChildMembersRequestDto",
      "namespace": "OneStream.Shared.Wcf.DimensionLibraryServiceDto",
      "type": "class",
      "modifiers": [
        "public",
        "sealed"
      ],
      "base_class": null,
      "interfaces": [
        "IClientDto",
        "IAuthenticatedClientDto"
      ],
      "generic_params": [],
      "constructors": [],
      "properties": [
        {
          "name": "XfBytes",
          "type": "string",
          "access": "public",
          "has_getter": true,
          "has_setter": true,
          "is_static": false
        },
        {
          "name": "CubeIdOrUnknown",
          "type": "int",
          "access": "public",
          "has_getter": true,
          "has_setter": true,
          "is_static": false
        },
        {
          "name": "DimTypeId",
          "type": "int",
          "access": "public",
          "has_getter": true,
          "has_setter": true,
          "is_static": false
        },
        {
          "name": "DimId",
          "type": "int",
          "access": "public",
          "has_getter": true,
          "has_setter": true,
          "is_static": false
        },
        {
          "name": "MemberId",
          "type": "int",
          "access": "public",
          "has_getter": true,
          "has_setter": true,
          "is_static": false
        }
      ],
      "methods": [],
      "events": [],
      "nested_types": [],
      "attributes": [],
      "source_file": "output/types/OneStream/Shared/Wcf/DimensionLibraryServiceDto/GetChildMembersRequestDto.cs"
    },
    {
      "name": "GetAllMembersCompressedRequestDto",
      "namespace": "OneStream.Shared.Wcf.DimensionLibraryServiceDto",
      "type": "class",
      "modifiers": [
        "public",
        "sealed"
      ],
      "base_class": null,
      "interfaces": [
        "IClientDto",
        "IAuthenticatedClientDto"
      ],
      "generic_params": [],
      "constructors": [],
      "properties": [
        {
          "name": "XfBytes",
          "type": "string",
          "access": "public",
          "has_getter": true,
          "has_setter": true,
          "is_static": false
        },
        {
          "name": "DimPk",
          "type": "DimPk",
          "access": "public",
          "has_getter": true,
          "has_setter": true,
          "is_static": false
        },
        {
          "name": "IncludeInheritedDims",
          "type": "bool",
          "access": "public",
          "has_getter": true,
          "has_setter": true,
          "is_static": false
        },
        {
          "name": "DimDisplayOptions",
          "type": "DimDisplayOptions",
          "access": "public",
          "has_getter": true,
          "has_setter": true,
          "is_static": false
        },
        {
          "name": "MemberDisplayOptions",
          "type": "MemberDisplayOptions",
          "access": "public",
          "has_getter": true,
          "has_setter": true,
          "is_static": false
        }
      ],
      "methods": [],
      "events": [],
      "nested_types": [],
      "attributes": [],
      "source_file": "output/types/OneStream/Shared/Wcf/DimensionLibraryServiceDto/GetAllMembersCompressedRequestDto.cs"
    },
    {
      "name": "RenameMemberRequestDto",
      "namespace": "OneStream.Shared.Wcf.DimensionLibraryServiceDto",
      "type": "class",
      "modifiers": [
        "public",
        "sealed"
      ],
      "base_class": null,
      "interfaces": [
        "IClientDto",
        "IAuthenticatedClientDto"
      ],
      "generic_params": [],
      "constructors": [],
      "properties": [
        {
          "name": "XfBytes",
          "type": "string",
          "access": "public",
          "has_getter": true,
          "has_setter": true,
          "is_static": false
        },
        {
          "name": "DimPk",
          "type": "DimPk",
          "access": "public",
          "has_getter": true,
          "has_setter": true,
          "is_static": false
        },
        {
          "name": "MemberName",
          "type": "string",
          "access": "public",
          "has_getter": true,
          "has_setter": true,
          "is_static": false
        },
        {
          "name": "NewMemberName",
          "type": "string",
          "access": "public",
          "has_getter": true,
          "has_setter": true,
          "is_static": false
        }
      ],
      "methods": [],
      "events": [],
      "nested_types": [],
      "attributes": [],
      "source_file": "output/types/OneStream/Shared/Wcf/DimensionLibraryServiceDto/RenameMemberRequestDto.cs"
    },
    {
      "name": "GetRelationshipsUsingFilterRequestDto",
      "namespace": "OneStream.Shared.Wcf.DimensionLibraryServiceDto",
      "type": "class",
      "modifiers": [
        "public",
        "sealed"
      ],
      "base_class": null,
      "interfaces": [
        "IClientDto",
        "IAuthenticatedClientDto"
      ],
      "generic_params": [],
      "constructors": [],
      "properties": [
        {
          "name": "XfBytes",
          "type": "string",
          "access": "public",
          "has_getter": true,
          "has_setter": true,
          "is_static": false
        },
        {
          "name": "DimPk",
          "type": "DimPk",
          "access": "public",
          "has_getter": true,
          "has_setter": true,
          "is_static": false
        },
        {
          "name": "MemberFilter",
          "type": "string",
          "access": "public",
          "has_getter": true,
          "has_setter": true,
          "is_static": false
        },
        {
          "name": "DimDisplayOptions",
          "type": "DimDisplayOptions",
          "access": "public",
          "has_getter": true,
          "has_setter": true,
          "is_static": false
        },
        {
          "name": "MemberDisplayOptions",
          "type": "MemberDisplayOptions",
          "access": "public",
          "has_getter": true,
          "has_setter": true,
          "is_static": false
        },
        {
          "name": "MemberDisplayOptionsForParent",
          "type": "MemberDisplayOptions",
          "access": "public",
          "has_getter": true,
          "has_setter": true,
          "is_static": false
        }
      ],
      "methods": [],
      "events": [],
      "nested_types": [],
      "attributes": [],
      "source_file": "output/types/OneStream/Shared/Wcf/DimensionLibraryServiceDto/GetRelationshipsUsingFilterRequestDto.cs"
    },
    {
      "name": "RenameDimRequestDto",
      "namespace": "OneStream.Shared.Wcf.DimensionLibraryServiceDto",
      "type": "class",
      "modifiers": [
        "public",
        "sealed"
      ],
      "base_class": null,
      "interfaces": [
        "IClientDto",
        "IAuthenticatedClientDto"
      ],
      "generic_params": [],
      "constructors": [],
      "properties": [
        {
          "name": "XfBytes",
          "type": "string",
          "access": "public",
          "has_getter": true,
          "has_setter": true,
          "is_static": false
        },
        {
          "name": "DimPk",
          "type": "DimPk",
          "access": "public",
          "has_getter": true,
          "has_setter": true,
          "is_static": false
        },
        {
          "name": "DimName",
          "type": "string",
          "access": "public",
          "has_getter": true,
          "has_setter": true,
          "is_static": false
        },
        {
          "name": "NewDimName",
          "type": "string",
          "access": "public",
          "has_getter": true,
          "has_setter": true,
          "is_static": false
        }
      ],
      "methods": [],
      "events": [],
      "nested_types": [],
      "attributes": [],
      "source_file": "output/types/OneStream/Shared/Wcf/DimensionLibraryServiceDto/RenameDimRequestDto.cs"
    },
    {
      "name": "GetMembersUsingFilterRequestDto",
      "namespace": "OneStream.Shared.Wcf.DimensionLibraryServiceDto",
      "type": "class",
      "modifiers": [
        "public",
        "sealed"
      ],
      "base_class": null,
      "interfaces": [
        "IClientDto",
        "IAuthenticatedClientDto"
      ],
      "generic_params": [],
      "constructors": [],
      "properties": [
        {
          "name": "XfBytes",
          "type": "string",
          "access": "public",
          "has_getter": true,
          "has_setter": true,
          "is_static": false
        },
        {
          "name": "DimPk",
          "type": "DimPk",
          "access": "public",
          "has_getter": true,
          "has_setter": true,
          "is_static": false
        },
        {
          "name": "MemberFilter",
          "type": "string",
          "access": "public",
          "has_getter": true,
          "has_setter": true,
          "is_static": false
        },
        {
          "name": "DimDisplayOptions",
          "type": "DimDisplayOptions",
          "access": "public",
          "has_getter": true,
          "has_setter": true,
          "is_static": false
        },
        {
          "name": "MemberDisplayOptions",
          "type": "MemberDisplayOptions",
          "access": "public",
          "has_getter": true,
          "has_setter": true,
          "is_static": false
        },
        {
          "name": "RemoveDuplicates",
          "type": "bool",
          "access": "public",
          "has_getter": true,
          "has_setter": true,
          "is_static": false
        }
      ],
      "methods": [],
      "events": [],
      "nested_types": [],
      "attributes": [],
      "source_file": "output/types/OneStream/Shared/Wcf/DimensionLibraryServiceDto/GetMembersUsingFilterRequestDto.cs"
    },
    {
      "name": "DeleteMemberRequestDto",
      "namespace": "OneStream.Shared.Wcf.DimensionLibraryServiceDto",
      "type": "class",
      "modifiers": [
        "public",
        "sealed"
      ],
      "base_class": null,
      "interfaces": [
        "IClientDto",
        "IAuthenticatedClientDto"
      ],
      "generic_params": [],
      "constructors": [],
      "properties": [
        {
          "name": "XfBytes",
          "type": "string",
          "access": "public",
          "has_getter": true,
          "has_setter": true,
          "is_static": false
        },
        {
          "name": "DimPk",
          "type": "DimPk",
          "access": "public",
          "has_getter": true,
          "has_setter": true,
          "is_static": false
        },
        {
          "name": "MemberPk",
          "type": "MemberPk",
          "access": "public",
          "has_getter": true,
          "has_setter": true,
          "is_static": false
        }
      ],
      "methods": [],
      "events": [],
      "nested_types": [],
      "attributes": [],
      "source_file": "output/types/OneStream/Shared/Wcf/DimensionLibraryServiceDto/DeleteMemberRequestDto.cs"
    },
    {
      "name": "SaveMemberAndRelationshipInfoRequestDto",
      "namespace": "OneStream.Shared.Wcf.DimensionLibraryServiceDto",
      "type": "class",
      "modifiers": [
        "public",
        "sealed"
      ],
      "base_class": null,
      "interfaces": [
        "IClientDto",
        "IAuthenticatedClientDto"
      ],
      "generic_params": [],
      "constructors": [],
      "properties": [
        {
          "name": "XfBytes",
          "type": "string",
          "access": "public",
          "has_getter": true,
          "has_setter": true,
          "is_static": false
        },
        {
          "name": "DimPk",
          "type": "DimPk",
          "access": "public",
          "has_getter": true,
          "has_setter": true,
          "is_static": false
        },
        {
          "name": "SaveMember",
          "type": "bool",
          "access": "public",
          "has_getter": true,
          "has_setter": true,
          "is_static": false
        },
        {
          "name": "Member",
          "type": "Member",
          "access": "public",
          "has_getter": true,
          "has_setter": true,
          "is_static": false
        },
        {
          "name": "SaveMemberProperties",
          "type": "bool",
          "access": "public",
          "has_getter": true,
          "has_setter": true,
          "is_static": false
        },
        {
          "name": "MemberProperties",
          "type": "VaryingMemberProperties",
          "access": "public",
          "has_getter": true,
          "has_setter": true,
          "is_static": false
        },
        {
          "name": "SaveDescriptions",
          "type": "bool",
          "access": "public",
          "has_getter": true,
          "has_setter": true,
          "is_static": false
        },
        {
          "name": "Descriptions",
          "type": "List<MemberDescription>",
          "access": "public",
          "has_getter": true,
          "has_setter": true,
          "is_static": false
        },
        {
          "name": "SaveRelationshipInfo",
          "type": "bool",
          "access": "public",
          "has_getter": true,
          "has_setter": true,
          "is_static": false
        },
        {
          "name": "RelationshipInfo",
          "type": "RelationshipInfo",
          "access": "public",
          "has_getter": true,
          "has_setter": true,
          "is_static": false
        },
        {
          "name": "RelationshipPositionOptions",
          "type": "RelationshipPositionOptions",
          "access": "public",
          "has_getter": true,
          "has_setter": true,
          "is_static": false
        },
        {
          "name": "IsNewMember",
          "type": "TriStateBool",
          "access": "public",
          "has_getter": true,
          "has_setter": true,
          "is_static": false
        }
      ],
      "methods": [],
      "events": [],
      "nested_types": [],
      "attributes": [],
      "source_file": "output/types/OneStream/Shared/Wcf/DimensionLibraryServiceDto/SaveMemberAndRelationshipInfoRequestDto.cs"
    },
    {
      "name": "GetChildMembersCompressedRequestDto",
      "namespace": "OneStream.Shared.Wcf.DimensionLibraryServiceDto",
      "type": "class",
      "modifiers": [
        "public",
        "sealed"
      ],
      "base_class": null,
      "interfaces": [
        "IClientDto",
        "IAuthenticatedClientDto"
      ],
      "generic_params": [],
      "constructors": [],
      "properties": [
        {
          "name": "XfBytes",
          "type": "string",
          "access": "public",
          "has_getter": true,
          "has_setter": true,
          "is_static": false
        },
        {
          "name": "CubeIdOrUnknown",
          "type": "int",
          "access": "public",
          "has_getter": true,
          "has_setter": true,
          "is_static": false
        },
        {
          "name": "DimTypeId",
          "type": "int",
          "access": "public",
          "has_getter": true,
          "has_setter": true,
          "is_static": false
        },
        {
          "name": "DimId",
          "type": "int",
          "access": "public",
          "has_getter": true,
          "has_setter": true,
          "is_static": false
        },
        {
          "name": "MemberId",
          "type": "int",
          "access": "public",
          "has_getter": true,
          "has_setter": true,
          "is_static": false
        }
      ],
      "methods": [],
      "events": [],
      "nested_types": [],
      "attributes": [],
      "source_file": "output/types/OneStream/Shared/Wcf/DimensionLibraryServiceDto/GetChildMembersCompressedRequestDto.cs"
    },
    {
      "name": "AddRelationshipRequestDto",
      "namespace": "OneStream.Shared.Wcf.DimensionLibraryServiceDto",
      "type": "class",
      "modifiers": [
        "public",
        "sealed"
      ],
      "base_class": null,
      "interfaces": [
        "IClientDto",
        "IAuthenticatedClientDto"
      ],
      "generic_params": [],
      "constructors": [],
      "properties": [
        {
          "name": "XfBytes",
          "type": "string",
          "access": "public",
          "has_getter": true,
          "has_setter": true,
          "is_static": false
        },
        {
          "name": "DimPk",
          "type": "DimPk",
          "access": "public",
          "has_getter": true,
          "has_setter": true,
          "is_static": false
        },
        {
          "name": "ParentId",
          "type": "int",
          "access": "public",
          "has_getter": true,
          "has_setter": true,
          "is_static": false
        },
        {
          "name": "ChildId",
          "type": "int",
          "access": "public",
          "has_getter": true,
          "has_setter": true,
          "is_static": false
        },
        {
          "name": "RelationshipPositionOptions",
          "type": "RelationshipPositionOptions",
          "access": "public",
          "has_getter": true,
          "has_setter": true,
          "is_static": false
        }
      ],
      "methods": [],
      "events": [],
      "nested_types": [],
      "attributes": [],
      "source_file": "output/types/OneStream/Shared/Wcf/DimensionLibraryServiceDto/AddRelationshipRequestDto.cs"
    },
    {
      "name": "GetMemberHierarchyInitInfoCompressedRequestDto",
      "namespace": "OneStream.Shared.Wcf.DimensionLibraryServiceDto",
      "type": "class",
      "modifiers": [
        "public",
        "sealed"
      ],
      "base_class": null,
      "interfaces": [
        "IClientDto",
        "IAuthenticatedClientDto"
      ],
      "generic_params": [],
      "constructors": [],
      "properties": [
        {
          "name": "XfBytes",
          "type": "string",
          "access": "public",
          "has_getter": true,
          "has_setter": true,
          "is_static": false
        },
        {
          "name": "SelectedItem",
          "type": "MemberHierarchySelectedItem",
          "access": "public",
          "has_getter": true,
          "has_setter": true,
          "is_static": false
        },
        {
          "name": "ExpandAll",
          "type": "bool",
          "access": "public",
          "has_getter": true,
          "has_setter": true,
          "is_static": false
        },
        {
          "name": "ExpandChildrenOfSelectedMember",
          "type": "bool",
          "access": "public",
          "has_getter": true,
          "has_setter": true,
          "is_static": false
        }
      ],
      "methods": [],
      "events": [],
      "nested_types": [],
      "attributes": [],
      "source_file": "output/types/OneStream/Shared/Wcf/DimensionLibraryServiceDto/GetMemberHierarchyInitInfoCompressedRequestDto.cs"
    }
  ],
  "interfaces": [],
  "structs": [],
  "delegates": [],
  "enums": []
}